[
    {
        "name": "国家卫健委 疫情通报",
        "parentUrl": "http://www.nhc.gov.cn/xcs/yqtb/list_gzbd.shtml",
        "tags": [
            "全国新增确诊病例249例",
            "<br/>境外输入病例156例",
            "广东59例",
            "上海55例",
            "广西7例",
            "天津6例",
            "福建6例",
            "云南6例",
            "北京4例",
            "浙江4例",
            "山东4例",
            "江苏2例",
            "重庆2例",
            "甘肃1例",
            "<br/>30例由无症状感染者转为确诊病例",
            "广东22例",
            "浙江4例",
            "广西4例",
            "<br/>本土病例93例",
            "内蒙古32例",
            "呼和浩特市30例",
            "呼伦贝尔市2例",
            "广东30例",
            "东莞市19例",
            "深圳市9例",
            "珠海市2例",
            "辽宁10例",
            "广西9例",
            "江苏4例",
            "云南3例",
            "临沧市2例",
            "红河哈尼族彝族自治州1例",
            "四川2例",
            "北京1例",
            "黑龙江1例",
            "福建1例",
            "1例由无症状感染者转为确诊病例"
        ],
        "updateTime": 1645840490617,
        "url": "http://www.nhc.gov.cn/xcs/yqtb/202202/0f96b0c483e747a39307b01174a85579.shtml",
        "title": "截至2月25日24时新型冠状病毒肺炎疫情最新情况",
        "content": [
            "2月25日0—24时，31个省（自治区、直辖市）和新疆生产建设兵团报告新增确诊病例249例。其中境外输入病例156例（广东59例，上海55例，广西7例，天津6例，福建6例，云南6例，北京4例，浙江4例，山东4例，江苏2例，重庆2例，甘肃1例），含30例由无症状感染者转为确诊病例（广东22例，浙江4例，广西4例）；本土病例93例（内蒙古32例，其中呼和浩特市30例、呼伦贝尔市2例；广东30例，其中东莞市19例、深圳市9例、珠海市2例；辽宁10例，均在葫芦岛市；广西9例，均在防城港市；江苏4例，均在苏州市；云南3例，其中临沧市2例、红河哈尼族彝族自治州1例；四川2例，均在成都市；北京1例，在朝阳区；黑龙江1例，在鸡西市；福建1例，在厦门市），含1例由无症状感染者转为确诊病例（在江苏）。无新增死亡病例。无新增疑似病例。<o:p></o:p>",
            "<font face=\"仿宋_GB2312\">当日新增治愈出院病例</font>72例，解除医学观察的密切接触者2608人，重症病例与前一日持平。<o:p></o:p>",
            "<a href=\"http://www.nhc.gov.cn/xcs/yqtb/202202/0f96b0c483e747a39307b01174a85579.shtml\" target=\"_blank\">更多信息直接访问卫健委官网</a>"
        ],
        "releaseTime": "2022-02-26"
    },
    {
        "name": "北京市卫健委 疫情通报",
        "parentUrl": "http://wjw.beijing.gov.cn/xwzx_20031/rdxws/",
        "tags": [
            "新增1例本土确诊病例",
            "<br/>新增4例境外输入确诊病例",
            "治愈出院4例"
        ],
        "updateTime": 1645840488620,
        "url": "http://wjw.beijing.gov.cn/xwzx_20031/rdxws/202202/t20220226_2617121.html",
        "title": "北京2月25日新增1例本土确诊病例 4例境外输入确诊病例 治愈出院4例",
        "content": [
            "2月25日0时至24时，新增1例本土确诊病例，无新增疑似病例和无症状感染者；新增4例境外输入确诊病例，无新增疑似病例和无症状感染者。治愈出院4例。",
            "<strong>本土确诊病例</strong>",
            "<a href=\"http://wjw.beijing.gov.cn/xwzx_20031/rdxws/202202/t20220226_2617121.html\" target=\"_blank\">更多信息直接访问卫健委官网</a>"
        ],
        "releaseTime": "2022-02-26"
    },
    {
        "name": "上海市卫健委 疫情通报",
        "parentUrl": "https://wsjkw.sh.gov.cn/xwfb/index.html",
        "tags": [
            "报告24例新增境外输入性新冠肺炎确诊病例",
            "新增治愈出院8例",
            "加拿大5例",
            "匈牙利1例",
            "阿联酋1例",
            "美国1例"
        ],
        "updateTime": 1645840488856,
        "url": "https://wsjkw.sh.gov.cn/xwfb/20220224/75b50eabdf2d4660b1d7caf4de932640.html",
        "title": "上海2022年2月23日，无新增本土新冠肺炎确诊病例 新增境外输入性新冠肺炎确诊病例24例 新增境外输入性无症状感染者8例 治愈出院8例",
        "content": [
            "2022年2月23日0—24时，通过口岸联防联控机制，报告24例新增境外输入性新冠肺炎确诊病例。新增治愈出院8例，其中来自加拿大5例，来自匈牙利1例，来自阿联酋1例，来自美国1例。",
            "<strong>病例1</strong>为台湾地区居民，在台湾地区生活，自台湾地区出发，于2022年2月13日抵达上海浦东国际机场，入关后即被集中隔离观察，其间出现症状。综合流行病学史、临床症状、实验室检测和影像学检查结果等，诊断为确诊病例。",
            "<a href=\"https://wsjkw.sh.gov.cn/xwfb/20220224/75b50eabdf2d4660b1d7caf4de932640.html\" target=\"_blank\">更多信息直接访问卫健委官网</a>"
        ],
        "releaseTime": "2022-02-24"
    },
    {
        "name": "天津市卫健委 疫情通报",
        "parentUrl": "http://wsjk.tj.gov.cn/XWZX6600/newyqfkdt/",
        "updateTime": 1641973535825,
        "url": "http://wsjk.tj.gov.cn/ZTZL1/ZTZL750/YQFKZL9424/YQTB7440/202201/t20220112_5776535.html",
        "title": "2022年1月12日天津市新型冠状病毒肺炎疫情情况",
        "content": [
            "截至1月11日，天津市累计报告新型冠状病毒肺炎确诊病例215例，出院病例145例，死亡病例3例，在院67例。",
            "累计报告境外输入性新型冠状病毒肺炎确诊病例490例，出院病例403例，在院87例。",
            "<a href=\"http://wsjk.tj.gov.cn/ZTZL1/ZTZL750/YQFKZL9424/YQTB7440/202201/t20220112_5776535.html\" target=\"_blank\">更多信息直接访问卫健委官网🔗</a>"
        ],
        "tags": [
            "天津市累计报告新型冠状病毒肺炎确诊病例215例",
            "出院病例145例",
            "死亡病例3例",
            "在院67例"
        ],
        "releaseTime": "2022-01-12      <span class=\"time\"> 08:45</span>"
    },
    {
        "name": "河南省卫健委 疫情通报",
        "parentUrl": "http://wsjkw.henan.gov.cn/ztzl/xxgzbdfyyqfk/yqtb/",
        "tags": [
            "10例本土确诊病例治愈出院",
            "2例境外输入无症状感染者解除医学观察"
        ],
        "updateTime": 1645840488655,
        "url": "http://wsjkw.henan.gov.cn/2022/02-26/2405065.html",
        "title": "截至2022年2月25日24时河南省新型冠状病毒肺炎疫情最新情况",
        "content": [
            "2月25日0—24时，全省无新增确诊病例、无症状感染者和疑似病例。10例本土确诊病例治愈出院，2例境外输入无症状感染者解除医学观察。",
            "2020年1月21日至2022年2月25日24时，全省累计报告确诊病例2664例（本土2508例、境外输入156例），现有住院病例18例（本土7例、境外输入11例），尚在医学观察的无症状感染者10例（境外输入10例）。累计追踪到密切接触者63988人，正在观察的密切接触者214人。"
        ],
        "releaseTime": "2022-02-26"
    },
    {
        "name": "陕西省卫健委 疫情通报",
        "parentUrl": "http://sxwjw.shaanxi.gov.cn/sy/wjyw/",
        "tags": [],
        "updateTime": 1642011635910,
        "url": "http://sxwjw.shaanxi.gov.cn/sy/wjyw/202201/t20220108_2206889.html",
        "title": "1月7日陕西新增46例本土确诊病例",
        "releaseTime": "2022-01-08 09:35"
    },
    {
        "name": "广东省卫健委 疫情通报",
        "parentUrl": "http://wsjkw.gd.gov.cn/zwyw_yqxx/index.html",
        "tags": [
            "全省新增本土确诊病例30例",
            "深圳9例",
            "珠海2例",
            "东莞19例",
            "新增本土无症状感染者9例"
        ],
        "updateTime": 1645840489291,
        "url": "http://wsjkw.gd.gov.cn/zwyw_yqxx/content/post_3829555.html",
        "title": "2022年2月26日广东省新冠肺炎疫情情况",
        "content": [
            "2月25日0-24时，全省新增本土确诊病例30例，深圳9例，珠海2例，东莞19例。新增本土无症状感染者9例，均为深圳报告。",
            "全省新增境外输入确诊病例59例（其中22例为无症状感染者转确诊），广州报告3例，分别来自韩国、老挝和土耳其；深圳报告26例，25例来自中国香港，1例来自韩国；珠海报告8例，东莞报告19例，江门报告3例，均来自中国香港。新增境外输入无症状感染者32例，广州报告3例，分别来自日本、菲律宾和泰国；佛山报告3例，分别来自韩国、缅甸和马来西亚；深圳报告8例，珠海报告2例，惠州报告2例，汕尾报告1例，东莞报告7例，中山报告1例，江门报告5例，均来自中国香港。新增出院16例，目前在院572例。",
            "<a href=\"http://wsjkw.gd.gov.cn/zwyw_yqxx/content/post_3829555.html\" target=\"_blank\">更多信息直接访问卫健委官网</a>"
        ],
        "releaseTime": "2022-02-26 08:59:22"
    },
    {
        "name": "深圳市卫健委 疫情通报",
        "parentUrl": "http://wjw.sz.gov.cn/yqxx/",
        "tags": [
            "深圳新增7例本土确诊病例和1例本土无症状感染者"
        ],
        "updateTime": 1642011635858,
        "url": "http://wjw.sz.gov.cn/yqxx/content/post_9515762.html",
        "title": "2022年1月12日深圳市新冠肺炎疫情情况",
        "content": [
            "1月11日0-24时，深圳新增7例本土确诊病例和1例本土无症状感染者。",
            "7例本土确诊病例为：",
            "<a href=\"http://wjw.sz.gov.cn/yqxx/content/post_9515762.html\" target=\"_blank\">更多信息直接访问卫健委官网</a>"
        ],
        "releaseTime": "2022-01-12 11:20:47"
    },
    {
        "name": "河北省卫健委 疫情通报",
        "parentUrl": "http://wsjkw.hebei.gov.cn/html/yqtb/",
        "tags": [],
        "updateTime": 1645840489814,
        "url": "http://wsjkw.hebei.gov.cn/html/yqtb/20220226/386382.html",
        "title": "2022年2月25日河北省新型冠状病毒肺炎疫情情况",
        "content": [
            "2022年2月25日0—24时，河北省无新增本土新型冠状病毒肺炎确诊病例，无新增本土无症状感染者。",
            "截至2月25日24时，河北省现有本土确诊病例0例；尚在医学观察本土无症状感染者1例。",
            "<a href=\"http://wsjkw.hebei.gov.cn/html/yqtb/20220226/386382.html\" target=\"_blank\">更多信息直接访问卫健委官网</a>"
        ],
        "releaseTime": "2022-02-26 08:14:25"
    }
]